sentinel/__init__.py
sentinel/actions/azure_emit_hash.py
sentinel/actions/send_to_sentinel.py
sentinel/actions/update_defender_xdr_alert.py
sentinel/actions/update_defender_xdr_incident.py
sentinel/config.py
sentinel/manifest.yml
sentinel/mapping/sentinel_incident.py
sentinel/mapping/xdr_alert.py
sentinel/mapping/xdr_alert_evidence.py
sentinel/odm/__init__.py
sentinel/odm/hit.py
sentinel/odm/models/sentinel.py
sentinel/routes/__init__.py
sentinel/routes/ingest.py
sentinel/utils/tenant_utils.py
howler_sentinel_plugin-0.2.0.189.dist-info/METADATA
howler_sentinel_plugin-0.2.0.189.dist-info/WHEEL
howler_sentinel_plugin-0.2.0.189.dist-info/entry_points.txt
howler_sentinel_plugin-0.2.0.189.dist-info/licenses/LICENSE
howler_sentinel_plugin-0.2.0.189.dist-info/RECORD
