Metadata-Version: 2.4
Name: howler-sentinel-plugin
Version: 0.2.0.189
Summary: A howler plugin for integration with Microsoft's Sentinel API
License: MIT
License-File: LICENSE
Author: CCCS
Author-email: analysis-development@cyber.gc.ca
Requires-Python: >=3.9.17, <4.0
Classifier: License :: OSI Approved :: MIT License
Classifier: Programming Language :: Python :: 3
Classifier: Programming Language :: Python :: 3.10
Classifier: Programming Language :: Python :: 3.11
Classifier: Programming Language :: Python :: 3.12
Classifier: Programming Language :: Python :: 3.13
Classifier: Programming Language :: Python :: 3.14
Requires-Dist: python-dateutil (>=2.9.0.post0,<3.0.0)
